enthusiast_common/__init__.py
enthusiast_common/agents/__init__.py
enthusiast_common/agents/base.py
enthusiast_common/builder/__init__.py
enthusiast_common/builder/base.py
enthusiast_common/callbacks/__init__.py
enthusiast_common/callbacks/base.py
enthusiast_common/config/__init__.py
enthusiast_common/config/base.py
enthusiast_common/config/prompts.py
enthusiast_common/errors/__init__.py
enthusiast_common/errors/base_agent_friendly_error.py
enthusiast_common/errors/retriever_error.py
enthusiast_common/injectors/__init__.py
enthusiast_common/injectors/base.py
enthusiast_common/interfaces.py
enthusiast_common/llm/__init__.py
enthusiast_common/llm/base.py
enthusiast_common/registry/__init__.py
enthusiast_common/registry/agents.py
enthusiast_common/registry/embeddings.py
enthusiast_common/registry/llm.py
enthusiast_common/registry/models.py
enthusiast_common/repositories/__init__.py
enthusiast_common/repositories/base.py
enthusiast_common/retrievers/__init__.py
enthusiast_common/retrievers/base.py
enthusiast_common/retrievers/base_product_retriever.py
enthusiast_common/retrievers/vector_store.py
enthusiast_common/services/conversation.py
enthusiast_common/services/file.py
enthusiast_common/structures.py
enthusiast_common/tools/__init__.py
enthusiast_common/tools/base.py
enthusiast_common/tools/files/list_files_tool.py
enthusiast_common/tools/files/perform_file_operation_tool.py
enthusiast_common/utils.py
enthusiast_common-1.5.0.dist-info/METADATA
enthusiast_common-1.5.0.dist-info/WHEEL
enthusiast_common-1.5.0.dist-info/licenses/LICENSE.md
enthusiast_common-1.5.0.dist-info/RECORD
