Metadata-Version: 2.4
Name: enthusiast-common
Version: 1.5.0
Summary: Core interfaces for developing custom Enthusiast plugins and integrations.
License-File: LICENSE.md
Author: Rafal Cymerys
Author-email: rafal@upsidelab.io
Requires-Python: >=3.10,<4.0
Classifier: Programming Language :: Python :: 3
Classifier: Programming Language :: Python :: 3.10
Classifier: Programming Language :: Python :: 3.11
Classifier: Programming Language :: Python :: 3.12
Classifier: Programming Language :: Python :: 3.13
Classifier: Programming Language :: Python :: 3.14
Requires-Dist: langchain-core (>=0.3.66,<0.4.0)
